[{"name": "Logitech G PRO X (AVG) [Shewi treble+ (U6T) Target]", "preamp": 0.0, "parametric": true, "bands": [{"type": 0, "channels": 0, "frequency": 90, "q": 0, "gain": 0.0, "color": 0}, {"type": 1, "channels": 0, "frequency": 10000, "q": 0, "gain": 0.0, "color": 0}, {"type": 3, "channels": 0, "frequency": 22, "q": 0.3, "gain": 10.4, "color": -2112025}, {"type": 3, "channels": 0, "frequency": 43, "q": 2.5, "gain": 1.2, "color": -13060459}, {"type": 3, "channels": 0, "frequency": 71, "q": 3.5, "gain": 1.0, "color": -7499016}, {"type": 3, "channels": 0, "frequency": 180, "q": 1.0, "gain": -2.9, "color": -214839}, {"type": 3, "channels": 0, "frequency": 370, "q": 2.9, "gain": 2.1, "color": -2136216}, {"type": 3, "channels": 0, "frequency": 590, "q": 2.3, "gain": -2.1, "color": -13397879}, {"type": 3, "channels": 0, "frequency": 1200, "q": 2.0, "gain": 1.7, "color": -14389271}, {"type": 3, "channels": 0, "frequency": 1900, "q": 5.0, "gain": 1.1, "color": -5620589}, {"type": 3, "channels": 0, "frequency": 2900, "q": 2.9, "gain": -1.8, "color": -11678708}, {"type": 3, "channels": 0, "frequency": 3700, "q": 5.0, "gain": 1.8, "color": -5858434}, {"type": 3, "channels": 0, "frequency": 4800, "q": 4.2, "gain": 3.5, "color": -7161746}, {"type": 3, "channels": 0, "frequency": 5100, "q": 5.0, "gain": 1.5, "color": -14104836}, {"type": 3, "channels": 0, "frequency": 8500, "q": 1.5, "gain": -4.7, "color": -14442164}, {"type": 3, "channels": 0, "frequency": 17000, "q": 1.7, "gain": 12.7, "color": -15702526}]}]